LICENSE.md
README.md
setup.py
discourse_docsify/__init__.py
discourse_docsify/app.py
discourse_docsify/cache.py
discourse_docsify/discourse_api.py
discourse_docsify/parser.py
discourse_docsify.egg-info/PKG-INFO
discourse_docsify.egg-info/SOURCES.txt
discourse_docsify.egg-info/dependency_links.txt
discourse_docsify.egg-info/requires.txt
discourse_docsify.egg-info/top_level.txt
discourse_docsify/static/__init__.py
discourse_docsify/static/index.html
discourse_docsify/static/template.md