Metadata-Version: 2.1
Name: discourse-docsify
Version: 1.0.0
Summary: Flask extension to add docsify (documentation) sourced from discourse (forum) content.
Home-page: https://github.com/guipenedo/discourse-docsify
Author: Guilherme Penedo
Author-email: nostrumg@gmail.com
License: MIT
Platform: UNKNOWN
Requires-Python: >=3.5
License-File: LICENSE.md
